wizard_vs_irs/__init__.py
wizard_vs_irs/run.py
wizard_vs_irs/assets/fonts/OFL.txt
wizard_vs_irs/assets/fonts/Roboto-Black.ttf
wizard_vs_irs/assets/graphics/button.png
wizard_vs_irs/assets/graphics/button_hovered.png
wizard_vs_irs/assets/graphics/irs_agent.png
wizard_vs_irs/assets/graphics/mage-dark.png
wizard_vs_irs/assets/graphics/mage-light.png
wizard_vs_irs/game/inventory.py
wizard_vs_irs/game/play.py
wizard_vs_irs/menus/main.py
wizard_vs_irs/menus/settings.py
wizard_vs_irs/menus/shop.py
wizard_vs_irs/utils/constants.py
wizard_vs_irs/utils/preload.py
wizard_vs_irs/utils/utils.py
wizard_vs_irs-0.1.5.dist-info/licenses/LICENSE
wizard_vs_irs-0.1.5.dist-info/METADATA
wizard_vs_irs-0.1.5.dist-info/WHEEL
wizard_vs_irs-0.1.5.dist-info/entry_points.txt
wizard_vs_irs-0.1.5.dist-info/top_level.txt
wizard_vs_irs-0.1.5.dist-info/RECORD
