Metadata-Version: 2.4
Name: wizard-vs-irs
Version: 0.1.5
Summary: Wizard vs IRS
Classifier: License :: OSI Approved :: GNU General Public License v3 (GPLv3)
Classifier: Programming Language :: Python :: 3
Classifier: Programming Language :: Python :: 3.11
Classifier: Operating System :: OS Independent
Requires-Python: >=3.11
License-File: LICENSE
Requires-Dist: arcade>=3.3.3
Requires-Dist: pypresence>=4.3.0
Dynamic: license-file
